schematizer/__init__.py
schematizer/exceptions.py
schematizer/key.py
schematizer/validators.py
schematizer/schemas/__init__.py
schematizer/schemas/base.py
schematizer/schemas/compound.py
schematizer/schemas/simple.py
schematizer/vendor/__init__.py
schematizer/vendor/django/__init__.py
schematizer/vendor/django/validators.py
schematizer-0.8.8.dist-info/LICENSE.rst
schematizer-0.8.8.dist-info/METADATA
schematizer-0.8.8.dist-info/WHEEL
schematizer-0.8.8.dist-info/top_level.txt
schematizer-0.8.8.dist-info/RECORD
