Metadata-Version: 2.1
Name: schematizer
Version: 0.8.8
Summary: A lightweight library for data marshalling/unmarshalling in Python
Home-page: https://github.com/eb08a167/schematizer
Author: Andrew Kiyko
Author-email: eb08a167@gmail.com
License: MIT
Platform: UNKNOWN
Classifier: Intended Audience :: Developers
Classifier: Programming Language :: Python :: 3
Requires-Python: >=3.6
